{
  "project_info": {
    "project_number": "104345071956",
    "firebase_url": "https://astronbags-925b3.firebaseio.com",
    "project_id": "astronbags-925b3",
    "storage_bucket": "astronbags-925b3.appspot.com"
  },
  "client": [
    {
      "client_info": {
        "mobilesdk_app_id": "1:104345071956:android:a046ac6c71e69eb4ee18c1",
        "android_client_info": {
          "package_name": "com.example.astron_bags"
        }
      },
      "oauth_client": [
        {
          "client_id": "104345071956-2v801dhnr7kh9p25s1tvv20i04d105hr.apps.googleusercontent.com",
          "client_type": 3
        }
      ],
      "api_key": [
        {
          "current_key": "AIzaSyCt4T0uNLLO96ArhfxtUiMz7wAGCtoMEuA"
        }
      ],
      "services": {
        "appinvite_service": {
          "other_platform_oauth_client": [
            {
              "client_id": "104345071956-2v801dhnr7kh9p25s1tvv20i04d105hr.apps.googleusercontent.com",
              "client_type": 3
            }
          ]
        }
      }
    }
  ],
  "configuration_version": "1"
}